locdataMAC/__init__.py
locdataMAC/activity.py
locdataMAC/analytics.py
locdataMAC/charts.py
locdataMAC/cutom_exception.py
locdataMAC/logger.py
locdataMAC/timer.py
locdataMAC-0.1.0.dist-info/LICENSE
locdataMAC-0.1.0.dist-info/METADATA
locdataMAC-0.1.0.dist-info/WHEEL
locdataMAC-0.1.0.dist-info/top_level.txt
locdataMAC-0.1.0.dist-info/RECORD
