Metadata-Version: 2.1
Name: locdataMAC
Version: 0.1.0
Summary: A small python package
Home-page: https://github.com/SachinMishra-ux/locdataMAC
Author: SachinMishra-ux
Author-email: sachin19566@gmail.com
License: MIT
Project-URL: Bug Tracker, https://github.com/SachinMishra-ux/locdataMAC/issues
Classifier: Programming Language :: Python :: 3.7
Classifier: Operating System :: OS Independent
Requires-Python: >=3.7
License-File: LICENSE
Requires-Dist: ensure (==1.0.2)
Requires-Dist: python-dateutil (==2.8.2)
Requires-Dist: pyobjc (==9.0.1)
Provides-Extra: testing
Requires-Dist: pytest (>=7.1.3) ; extra == 'testing'
Requires-Dist: mypy (>=0.971) ; extra == 'testing'
Requires-Dist: flake8 (>=5.0.4) ; extra == 'testing'
Requires-Dist: tox (>=3.25.1) ; extra == 'testing'
Requires-Dist: black (>=22.8.0) ; extra == 'testing'
